README.txt
setup.py
src/Products/__init__.py
src/Products.PASGroupsFromLDAP.egg-info/PKG-INFO
src/Products.PASGroupsFromLDAP.egg-info/SOURCES.txt
src/Products.PASGroupsFromLDAP.egg-info/dependency_links.txt
src/Products.PASGroupsFromLDAP.egg-info/entry_points.txt
src/Products.PASGroupsFromLDAP.egg-info/namespace_packages.txt
src/Products.PASGroupsFromLDAP.egg-info/not-zip-safe
src/Products.PASGroupsFromLDAP.egg-info/requires.txt
src/Products.PASGroupsFromLDAP.egg-info/top_level.txt
src/Products/PASGroupsFromLDAP/LICENSE.txt
src/Products/PASGroupsFromLDAP/README.txt
src/Products/PASGroupsFromLDAP/__init__.py
src/Products/PASGroupsFromLDAP/_plugin.py
src/Products/PASGroupsFromLDAP/configure.zcml
src/Products/PASGroupsFromLDAP/exportimport.py
src/Products/PASGroupsFromLDAP/profiles.zcml
src/Products/PASGroupsFromLDAP/setuphandlers.py
src/Products/PASGroupsFromLDAP/docs/__init__.py
src/Products/PASGroupsFromLDAP/docs/propertiesplugin.txt
src/Products/PASGroupsFromLDAP/profile/import_steps.xml
src/Products/PASGroupsFromLDAP/profile/metadata.xml
src/Products/PASGroupsFromLDAP/profile/pasgroupsfromldap_marker.txt
src/Products/PASGroupsFromLDAP/tests/__init__.py
src/Products/PASGroupsFromLDAP/tests/framework.py
src/Products/PASGroupsFromLDAP/tests/runalltests.py
src/Products/PASGroupsFromLDAP/tests/test_doctests.py
src/Products/PASGroupsFromLDAP/www/addGroupsFromLDAPMultiPlugin.zpt
src/Products/PASGroupsFromLDAP/www/ldap.gif
src/Products/PASGroupsFromLDAP/www/manage_base_dns.zpt