Metadata-Version: 1.0
Name: Products.PASGroupsFromLDAP
Version: 1.2.3
Summary: Zope 2 PAS Plugin providing groups from LDAP directory
Home-page: UNKNOWN
Author: Jens Klein, Robert Niederreiter
Author-email: jens@bluedynamics.com, rnix@squarewave.at
License: UNKNOWN
Keywords: zope2
Platform: UNKNOWN
Classifier: Development Status :: 5 - Production/Stable
Classifier: Environment :: Web Environment
Classifier: Framework :: Zope2
Classifier: Operating System :: OS Independent
Classifier: Programming Language :: Python
